python_simplestreams-0.1.0.post59.data/data/lib/simplestreams/hook-check-downloads
python_simplestreams-0.1.0.post59.data/data/lib/simplestreams/hook-debug
python_simplestreams-0.1.0.post59.data/data/lib/simplestreams/hook-glance
python_simplestreams-0.1.0.post59.data/data/lib/simplestreams/hook-image-id
python_simplestreams-0.1.0.post59.data/data/share/doc/simplestreams/README
python_simplestreams-0.1.0.post59.data/scripts/json2streams
python_simplestreams-0.1.0.post59.data/scripts/sstream-mirror
python_simplestreams-0.1.0.post59.data/scripts/sstream-mirror-glance
python_simplestreams-0.1.0.post59.data/scripts/sstream-query
python_simplestreams-0.1.0.post59.data/scripts/sstream-sync
simplestreams/__init__.py
simplestreams/checksum_util.py
simplestreams/contentsource.py
simplestreams/filters.py
simplestreams/generate_simplestreams.py
simplestreams/json2streams.py
simplestreams/log.py
simplestreams/openstack.py
simplestreams/util.py
simplestreams/mirrors/__init__.py
simplestreams/mirrors/command_hook.py
simplestreams/mirrors/glance.py
simplestreams/objectstores/__init__.py
simplestreams/objectstores/s3.py
simplestreams/objectstores/swift.py
python_simplestreams-0.1.0.post59.dist-info/LICENSE
python_simplestreams-0.1.0.post59.dist-info/METADATA
python_simplestreams-0.1.0.post59.dist-info/WHEEL
python_simplestreams-0.1.0.post59.dist-info/top_level.txt
python_simplestreams-0.1.0.post59.dist-info/RECORD
